grpc_gcp/__init__.py
grpc_gcp/_channel.py
grpc_gcp/proto/__init__.py
grpc_gcp/proto/grpc_gcp_pb2.py
grpcio_gcp-0.2.1.dist-info/METADATA
grpcio_gcp-0.2.1.dist-info/RECORD
grpcio_gcp-0.2.1.dist-info/WHEEL
grpcio_gcp-0.2.1.dist-info/top_level.txt
