Metadata-Version: 2.1
Name: grpcio-gcp
Version: 0.2.1
Summary: gRPC extensions for Google Cloud Platform
Home-page: https://grpc.io
Author: The gRPC-GCP Authors
Author-email: grpc-io@googlegroups.com
License: Apache License 2.0
Platform: UNKNOWN
Classifier: Development Status :: 5 - Production/Stable
Classifier: Programming Language :: Python
Classifier: Programming Language :: Python :: 2
Classifier: Programming Language :: Python :: 2.7
Classifier: Programming Language :: Python :: 3
Classifier: Programming Language :: Python :: 3.4
Classifier: Programming Language :: Python :: 3.5
Classifier: Programming Language :: Python :: 3.6
Classifier: License :: OSI Approved :: Apache Software License
Requires-Dist: grpcio (>=1.12.0)
